LICENSE
MANIFEST.in
README.rst
runtests.sh
setup.cfg
setup.py
demos/blog/README
demos/blog/blog.py
demos/blog/schema.sql
demos/blog/static/blog.css
demos/blog/templates/archive.html
demos/blog/templates/base.html
demos/blog/templates/compose.html
demos/blog/templates/create_author.html
demos/blog/templates/entry.html
demos/blog/templates/feed.xml
demos/blog/templates/home.html
demos/blog/templates/login.html
demos/blog/templates/modules/entry.html
demos/chat/chatdemo.py
demos/chat/static/chat.css
demos/chat/static/chat.js
demos/chat/templates/index.html
demos/chat/templates/message.html
demos/facebook/README
demos/facebook/facebook.py
demos/facebook/static/facebook.css
demos/facebook/static/facebook.js
demos/facebook/templates/stream.html
demos/facebook/templates/modules/post.html
demos/file_upload/file_receiver.py
demos/file_upload/file_uploader.py
demos/helloworld/helloworld.py
demos/s3server/s3server.py
demos/tcpecho/client.py
demos/tcpecho/server.py
demos/twitter/home.html
demos/twitter/twitterdemo.py
demos/websocket/chatdemo.py
demos/websocket/static/chat.css
demos/websocket/static/chat.js
demos/websocket/templates/index.html
demos/websocket/templates/message.html
demos/webspider/webspider.py
docs/Makefile
docs/asyncio.rst
docs/auth.rst
docs/autoreload.rst
docs/caresresolver.rst
docs/concurrent.rst
docs/conf.py
docs/coroutine.rst
docs/escape.rst
docs/faq.rst
docs/favicon.ico
docs/gen.rst
docs/guide.rst
docs/http.rst
docs/http1connection.rst
docs/httpclient.rst
docs/httpserver.rst
docs/httputil.rst
docs/index.rst
docs/integration.rst
docs/ioloop.rst
docs/iostream.rst
docs/locale.rst
docs/locks.rst
docs/log.rst
docs/netutil.rst
docs/networking.rst
docs/options.rst
docs/process.rst
docs/queues.rst
docs/releases.rst
docs/requirements.txt
docs/routing.rst
docs/tcpclient.rst
docs/tcpserver.rst
docs/template.rst
docs/testing.rst
docs/tornado.png
docs/twisted.rst
docs/util.rst
docs/utilities.rst
docs/web.rst
docs/webframework.rst
docs/websocket.rst
docs/wsgi.rst
tornado_gcp.egg-info/PKG-INFO
tornado_gcp.egg-info/SOURCES.txt
tornado_gcp.egg-info/dependency_links.txt
tornado_gcp.egg-info/top_level.txt