Metadata-Version: 1.2
Name: tornado-gcp
Version: 6.1.3
Summary: Tornado is a Python web framework and asynchronous networking library, originally developed at FriendFeed.
Home-page: http://www.tornadoweb.org/
Author: Facebook
Author-email: python-tornado@googlegroups.com
License: http://www.apache.org/licenses/LICENSE-2.0
Platform: UNKNOWN
Classifier: License :: OSI Approved :: Apache Software License
Classifier: Programming Language :: Python :: 3
Classifier: Programming Language :: Python :: 3.5
Classifier: Programming Language :: Python :: 3.6
Classifier: Programming Language :: Python :: 3.7
Classifier: Programming Language :: Python :: 3.8
Classifier: Programming Language :: Python :: 3.9
Classifier: Programming Language :: Python :: Implementation :: CPython
Classifier: Programming Language :: Python :: Implementation :: PyPy
Requires-Python: >= 3.5
